<?xml version="1.0" encoding="utf-8" ?>
<c2eventsheet>
    <!--All the 'name' attributes are ignored by Construct 2 - they are there for readability only.-->
    <name>Level9</name>
    <events>
        <comment>Global ruleset</comment>
        <event-block sid="8803953894442426">
            <conditions>
                <condition id="-2" name="On start of layout" sid="231991941816332" type="System" />
            </conditions>
            <actions>
                <action id="2" name="Stop" sid="3266423307072616" type="Player" />
            </actions>
        </event-block>
        <event-block sid="9393544399850229">
            <conditions>
                <condition id="2" name="Key is down" sid="5198998975023376" type="Keyboard">
                    <param id="0" name="Key">37 (Left arrow)</param>
                </condition>
            </conditions>
            <actions>
                <action id="4" name="Set animation" sid="7898667692816261" type="Player">
                    <param id="0" name="Animation">&quot;Back&quot;</param>
                    <param id="1" name="From">0</param>
                </action>
            </actions>
        </event-block>
        <event-block sid="9184933173062741">
            <conditions>
                <condition id="2" name="Key is down" sid="2640358541523168" type="Keyboard">
                    <param id="0" name="Key">39 (Right arrow)</param>
                </condition>
            </conditions>
            <actions>
                <action id="4" name="Set animation" sid="8658136268869121" type="Player">
                    <param id="0" name="Animation">&quot;Forward&quot;</param>
                    <param id="1" name="From">0</param>
                </action>
            </actions>
        </event-block>
        <event-block sid="6806335707809105">
            <conditions>
                <condition id="2" name="Key is down" sid="7119226251133729" type="Keyboard">
                    <param id="0" name="Key">38 (Up arrow)</param>
                </condition>
                <condition id="2" inverted="1" name="Key is down" sid="2385044181934385" type="Keyboard">
                    <param id="0" name="Key">39 (Right arrow)</param>
                </condition>
                <condition id="2" inverted="1" name="Key is down" sid="7084828831721425" type="Keyboard">
                    <param id="0" name="Key">37 (Left arrow)</param>
                </condition>
            </conditions>
            <actions>
                <action id="4" name="Set animation" sid="76291241218051" type="Player">
                    <param id="0" name="Animation">&quot;Back&quot;</param>
                    <param id="1" name="From">0</param>
                </action>
            </actions>
        </event-block>
        <event-block sid="4600755813583128">
            <conditions>
                <condition id="2" name="Key is down" sid="8493216171609081" type="Keyboard">
                    <param id="0" name="Key">40 (Down arrow)</param>
                </condition>
                <condition id="2" inverted="1" name="Key is down" sid="459450386736061" type="Keyboard">
                    <param id="0" name="Key">39 (Right arrow)</param>
                </condition>
                <condition id="2" inverted="1" name="Key is down" sid="2495039992776561" type="Keyboard">
                    <param id="0" name="Key">37 (Left arrow)</param>
                </condition>
            </conditions>
            <actions>
                <action id="4" name="Set animation" sid="5789411546917652" type="Player">
                    <param id="0" name="Animation">&quot;Forward&quot;</param>
                    <param id="1" name="From">0</param>
                </action>
            </actions>
        </event-block>
        <event-block sid="1298114655907693">
            <conditions>
                <condition id="7" name="On any key released" sid="4247230425168133" type="Keyboard" />
            </conditions>
            <actions>
                <action id="2" name="Stop" sid="6190179772956287" type="Player" />
            </actions>
        </event-block>
        <event-block sid="1923193485664765">
            <conditions>
                <condition id="9" inverted="1" name="Is overlapping at offset" sid="581258019884719" type="Player">
                    <param id="0" name="Object">Tiles</param>
                    <param id="1" name="Offset X">30</param>
                    <param id="2" name="Offset Y">30</param>
                </condition>
            </conditions>
            <actions>
                <action id="-26" name="Restart layout" sid="6734389195923694" type="System" />
                <action id="-11" name="Subtract from" sid="9198932503934093" type="System">
                    <param id="0" name="Variable">Lives</param>
                    <param id="1" name="Value">1</param>
                </action>
            </actions>
        </event-block>
        <comment>Lifebar</comment>
        <event-block sid="18561824383251">
            <conditions>
                <condition id="-14" name="Compare variable" sid="1888337739203549" type="System">
                    <param id="0" name="Variable">Lives</param>
                    <param id="1" name="Comparison">0</param>
                    <param id="2" name="Value">5</param>
                </condition>
            </conditions>
            <actions>
                <action id="5" name="Set frame" sid="995883111062256" type="Lifebar">
                    <param id="0" name="Frame number">5</param>
                </action>
            </actions>
        </event-block>
        <event-block sid="2889278039747532">
            <conditions>
                <condition id="-14" name="Compare variable" sid="735279443824759" type="System">
                    <param id="0" name="Variable">Lives</param>
                    <param id="1" name="Comparison">0</param>
                    <param id="2" name="Value">4</param>
                </condition>
            </conditions>
            <actions>
                <action id="5" name="Set frame" sid="8214924307233072" type="Lifebar">
                    <param id="0" name="Frame number">4</param>
                </action>
            </actions>
        </event-block>
        <event-block sid="9031003067241039">
            <conditions>
                <condition id="-14" name="Compare variable" sid="2574486947284077" type="System">
                    <param id="0" name="Variable">Lives</param>
                    <param id="1" name="Comparison">0</param>
                    <param id="2" name="Value">3</param>
                </condition>
            </conditions>
            <actions>
                <action id="5" name="Set frame" sid="2288767616138082" type="Lifebar">
                    <param id="0" name="Frame number">3</param>
                </action>
            </actions>
        </event-block>
        <event-block sid="7250310264477887">
            <conditions>
                <condition id="-14" name="Compare variable" sid="3629978452342268" type="System">
                    <param id="0" name="Variable">Lives</param>
                    <param id="1" name="Comparison">0</param>
                    <param id="2" name="Value">2</param>
                </condition>
            </conditions>
            <actions>
                <action id="5" name="Set frame" sid="722055537939253" type="Lifebar">
                    <param id="0" name="Frame number">2</param>
                </action>
            </actions>
        </event-block>
        <event-block sid="5032365368482425">
            <conditions>
                <condition id="-14" name="Compare variable" sid="7048058944455813" type="System">
                    <param id="0" name="Variable">Lives</param>
                    <param id="1" name="Comparison">0</param>
                    <param id="2" name="Value">1</param>
                </condition>
            </conditions>
            <actions>
                <action id="5" name="Set frame" sid="3153968947718069" type="Lifebar">
                    <param id="0" name="Frame number">1</param>
                </action>
            </actions>
        </event-block>
        <event-block sid="7128791102522922">
            <conditions>
                <condition id="-14" name="Compare variable" sid="9082680615220339" type="System">
                    <param id="0" name="Variable">Lives</param>
                    <param id="1" name="Comparison">0</param>
                    <param id="2" name="Value">0</param>
                </condition>
            </conditions>
            <actions>
                <action id="5" name="Set frame" sid="5721738550487831" type="Lifebar">
                    <param id="0" name="Frame number">0</param>
                </action>
            </actions>
        </event-block>
        <event-block sid="5154136682663086">
            <conditions>
                <condition id="-14" name="Compare variable" sid="7865614950113114" type="System">
                    <param id="0" name="Variable">Lives</param>
                    <param id="1" name="Comparison">2</param>
                    <param id="2" name="Value">0</param>
                </condition>
            </conditions>
            <actions>
                <action id="-2" name="Go to layout" sid="15351077015844" type="System">
                    <param id="0" name="Layout">MainMenu</param>
                </action>
            </actions>
        </event-block>
        <comment>Level specific mechanics</comment>
        <event-block sid="8522244735476431">
            <conditions>
                <condition id="-6" name="Every X seconds" sid="52727716141813" type="System">
                    <param id="0" name="Interval (seconds)">2</param>
                </condition>
                <condition id="-9" name="Is visible" sid="4121391675746999" type="Vanisher" />
            </conditions>
            <actions>
                <action id="-15" name="Set visible" sid="143652614803424" type="Vanisher">
                    <param id="0" name="Visibility">0</param>
                </action>
            </actions>
        </event-block>
        <event-block sid="2497008489212522">
            <conditions>
                <condition id="-6" name="Every X seconds" sid="3964244842493544" type="System">
                    <param id="0" name="Interval (seconds)">4</param>
                </condition>
                <condition id="-9" inverted="1" name="Is visible" sid="416110277646222" type="Vanisher" />
            </conditions>
            <actions>
                <action id="-15" name="Set visible" sid="3876361656165513" type="Vanisher">
                    <param id="0" name="Visibility">1</param>
                </action>
            </actions>
        </event-block>
        <event-block sid="6681241842952423">
            <conditions>
                <condition id="1" name="Is overlapping another object" sid="5012338514722376" type="Player">
                    <param id="0" name="Object">Vanisher</param>
                </condition>
                <condition id="-9" inverted="1" name="Is visible" sid="6923587214909937" type="Vanisher" />
            </conditions>
            <actions>
                <action id="-26" name="Restart layout" sid="789524224516242" type="System" />
                <action id="-11" name="Subtract from" sid="6527883803504532" type="System">
                    <param id="0" name="Variable">Lives</param>
                    <param id="1" name="Value">1</param>
                </action>
            </actions>
        </event-block>
        <event-block sid="5014119485678399">
            <conditions>
                <condition id="1" name="Is overlapping another object" sid="2074288013218306" type="Player">
                    <param id="0" name="Object">Eraser</param>
                </condition>
                <condition id="-6" name="Every X seconds" sid="9845497407289353" type="System">
                    <param id="0" name="Interval (seconds)">0.2</param>
                </condition>
            </conditions>
            <actions>
                <action id="-12" name="Subtract from" sid="3510339772756522" type="Eraser">
                    <param id="0" name="Instance variable">Transparency</param>
                    <param id="1" name="Value">10</param>
                </action>
                <action id="-16" name="Set opacity" sid="1780313919712536" type="Eraser">
                    <param id="0" name="Opacity">Eraser.Transparency</param>
                </action>
            </actions>
        </event-block>
        <event-block sid="6839962667057586">
            <conditions>
                <condition id="1" name="Is overlapping another object" sid="6786808867402442" type="Player">
                    <param id="0" name="Object">Eraser</param>
                </condition>
                <condition id="-10" name="Compare opacity" sid="3137862954020743" type="Eraser">
                    <param id="0" name="Comparison">2</param>
                    <param id="1" name="Opacity">10</param>
                </condition>
            </conditions>
            <actions>
                <action id="-26" name="Restart layout" sid="7918265852224633" type="System" />
                <action id="-11" name="Subtract from" sid="5673085031610401" type="System">
                    <param id="0" name="Variable">Lives</param>
                    <param id="1" name="Value">1</param>
                </action>
            </actions>
        </event-block>
        <event-block sid="7228975264863965">
            <conditions>
                <condition id="1" name="Is overlapping another object" sid="6508084599130872" type="Player">
                    <param id="0" name="Object">Essence_sprite</param>
                </condition>
                <condition id="-14" name="Pick by unique ID" sid="8465741793620116" type="Essence_sprite">
                    <param id="0" name="Unique ID">274</param>
                </condition>
                <condition id="-14" name="Pick by unique ID" sid="3842331447943469" type="Essence">
                    <param id="0" name="Unique ID">273</param>
                </condition>
            </conditions>
            <actions>
                <action id="-9" name="Destroy" sid="3171339361540475" type="Essence" />
                <action id="-10" name="Add to" sid="2877802870036474" type="System">
                    <param id="0" name="Variable">Essences</param>
                    <param id="1" name="Value">1</param>
                </action>
            </actions>
        </event-block>
        <event-block sid="6169622539863865">
            <conditions>
                <condition id="1" name="Is overlapping another object" sid="6199033055919161" type="Player">
                    <param id="0" name="Object">Goal</param>
                </condition>
            </conditions>
            <actions>
                <action id="0" name="Play" sid="5403338028928168" type="Audio">
                    <param id="0" name="Audio file">Next_Level</param>
                    <param id="2" name="Loop">0</param>
                    <param id="3" name="Volume">0</param>
                    <param id="1" name="Tag (optional)">&quot;&quot;</param>
                </action>
                <action id="-10" name="Add to" sid="6289723460015478" type="System">
                    <param id="0" name="Variable">Lives</param>
                    <param id="1" name="Value">1</param>
                </action>
                <action id="-2" name="Go to layout" sid="5200789696337985" type="System">
                    <param id="0" name="Layout">Level10</param>
                </action>
            </actions>
        </event-block>
        <event-block sid="2789061514045373">
            <conditions>
                <condition id="0" name="On collision with another object" sid="998448319387097" type="Player">
                    <param id="0" name="Object">Essence_sprite</param>
                </condition>
            </conditions>
            <actions>
                <action id="0" name="Play" sid="2125182835661265" type="Audio">
                    <param id="0" name="Audio file">Collect</param>
                    <param id="2" name="Loop">0</param>
                    <param id="3" name="Volume">0</param>
                    <param id="1" name="Tag (optional)">&quot;&quot;</param>
                </action>
                <action id="-9" name="Destroy" sid="4702348998350967" type="Essence_sprite" />
            </actions>
        </event-block>
        <event-block sid="2357132210063261">
            <conditions>
                <condition id="-19" name="On destroyed" sid="4928142654195675" type="Player" />
            </conditions>
            <actions>
                <action id="0" name="Play" sid="6313148086768952" type="Audio">
                    <param id="0" name="Audio file">Death</param>
                    <param id="2" name="Loop">0</param>
                    <param id="3" name="Volume">0</param>
                    <param id="1" name="Tag (optional)">&quot;&quot;</param>
                </action>
            </actions>
        </event-block>
        <event-block sid="8579898319992422">
            <conditions>
                <condition id="0" name="On collision with another object" sid="8120963379990148" type="Player">
                    <param id="0" name="Object">Sprite2</param>
                </condition>
            </conditions>
            <actions>
                <action id="-11" name="Subtract from" sid="3396848469003546" type="System">
                    <param id="0" name="Variable">Lives</param>
                    <param id="1" name="Value">1</param>
                </action>
                <action id="-26" name="Restart layout" sid="2287576968842196" type="System" />
            </actions>
        </event-block>
    </events>
</c2eventsheet>
